{
  "TextFileContent54Objects": [
    {
      "ID": "oval:org.altlinux.errata:obj:1001",
      "Version": "1",
      "comment": "Evaluate `/etc/os-release` file content",
      "Path": {
        "dataType": "string",
        "Text": "/etc"
      },
      "Filepath": {
        "Datatype": "string",
        "Text": "os-release"
      },
      "Pattern": {
        "Datatype": "string",
        "Operation": "pattern match",
        "Text": "cpe:\\/o:alt:(?!sp)[a-z\\-]+:p?(\\d+)(?:\\.\\d)*"
      },
      "Instance": {
        "Datatype": "int",
        "Text": "1"
      }
    }
  ],
  "RpmInfoObjects": [
    {
      "ID": "oval:org.altlinux.errata:obj:20211531001",
      "Version": "1",
      "comment": "kernel-doc-old is installed",
      "Name": "kernel-doc-old"
    },
    {
      "ID": "oval:org.altlinux.errata:obj:20211531002",
      "Version": "1",
      "comment": "kernel-headers-modules-old-def is installed",
      "Name": "kernel-headers-modules-old-def"
    },
    {
      "ID": "oval:org.altlinux.errata:obj:20211531003",
      "Version": "1",
      "comment": "kernel-headers-old-def is installed",
      "Name": "kernel-headers-old-def"
    },
    {
      "ID": "oval:org.altlinux.errata:obj:20211531004",
      "Version": "1",
      "comment": "kernel-image-domU-old-def is installed",
      "Name": "kernel-image-domU-old-def"
    },
    {
      "ID": "oval:org.altlinux.errata:obj:20211531005",
      "Version": "1",
      "comment": "kernel-image-old-def is installed",
      "Name": "kernel-image-old-def"
    },
    {
      "ID": "oval:org.altlinux.errata:obj:20211531006",
      "Version": "1",
      "comment": "kernel-modules-drm-ancient-old-def is installed",
      "Name": "kernel-modules-drm-ancient-old-def"
    },
    {
      "ID": "oval:org.altlinux.errata:obj:20211531007",
      "Version": "1",
      "comment": "kernel-modules-drm-nouveau-old-def is installed",
      "Name": "kernel-modules-drm-nouveau-old-def"
    },
    {
      "ID": "oval:org.altlinux.errata:obj:20211531008",
      "Version": "1",
      "comment": "kernel-modules-drm-old-def is installed",
      "Name": "kernel-modules-drm-old-def"
    },
    {
      "ID": "oval:org.altlinux.errata:obj:20211531009",
      "Version": "1",
      "comment": "kernel-modules-drm-radeon-old-def is installed",
      "Name": "kernel-modules-drm-radeon-old-def"
    },
    {
      "ID": "oval:org.altlinux.errata:obj:20211531010",
      "Version": "1",
      "comment": "kernel-modules-ide-old-def is installed",
      "Name": "kernel-modules-ide-old-def"
    },
    {
      "ID": "oval:org.altlinux.errata:obj:20211531011",
      "Version": "1",
      "comment": "kernel-modules-staging-old-def is installed",
      "Name": "kernel-modules-staging-old-def"
    },
    {
      "ID": "oval:org.altlinux.errata:obj:20211531012",
      "Version": "1",
      "comment": "kernel-modules-v4l-old-def is installed",
      "Name": "kernel-modules-v4l-old-def"
    }
  ]
}