{
  "TextFileContent54Objects": [
    {
      "ID": "oval:org.altlinux.errata:obj:2001",
      "Version": "1",
      "comment": "Evaluate `/etc/os-release` file content",
      "Path": {
        "dataType": "string",
        "Text": "/etc"
      },
      "Filepath": {
        "Datatype": "string",
        "Text": "os-release"
      },
      "Pattern": {
        "Datatype": "string",
        "Operation": "pattern match",
        "Text": "cpe:\\/o:alt:(?!sp)[a-z\\-]+:p?(\\d+)(?:\\.\\d)*"
      },
      "Instance": {
        "Datatype": "int",
        "Text": "1"
      }
    }
  ],
  "RpmInfoObjects": [
    {
      "ID": "oval:org.altlinux.errata:obj:20234390001",
      "Version": "1",
      "comment": "libqt5-concurrent is installed",
      "Name": "libqt5-concurrent"
    },
    {
      "ID": "oval:org.altlinux.errata:obj:20234390002",
      "Version": "1",
      "comment": "libqt5-core is installed",
      "Name": "libqt5-core"
    },
    {
      "ID": "oval:org.altlinux.errata:obj:20234390003",
      "Version": "1",
      "comment": "libqt5-dbus is installed",
      "Name": "libqt5-dbus"
    },
    {
      "ID": "oval:org.altlinux.errata:obj:20234390004",
      "Version": "1",
      "comment": "libqt5-eglfsdeviceintegration is installed",
      "Name": "libqt5-eglfsdeviceintegration"
    },
    {
      "ID": "oval:org.altlinux.errata:obj:20234390005",
      "Version": "1",
      "comment": "libqt5-eglfskmssupport is installed",
      "Name": "libqt5-eglfskmssupport"
    },
    {
      "ID": "oval:org.altlinux.errata:obj:20234390006",
      "Version": "1",
      "comment": "libqt5-gui is installed",
      "Name": "libqt5-gui"
    },
    {
      "ID": "oval:org.altlinux.errata:obj:20234390007",
      "Version": "1",
      "comment": "libqt5-network is installed",
      "Name": "libqt5-network"
    },
    {
      "ID": "oval:org.altlinux.errata:obj:20234390008",
      "Version": "1",
      "comment": "libqt5-opengl is installed",
      "Name": "libqt5-opengl"
    },
    {
      "ID": "oval:org.altlinux.errata:obj:20234390009",
      "Version": "1",
      "comment": "libqt5-printsupport is installed",
      "Name": "libqt5-printsupport"
    },
    {
      "ID": "oval:org.altlinux.errata:obj:20234390010",
      "Version": "1",
      "comment": "libqt5-sql is installed",
      "Name": "libqt5-sql"
    },
    {
      "ID": "oval:org.altlinux.errata:obj:20234390011",
      "Version": "1",
      "comment": "libqt5-test is installed",
      "Name": "libqt5-test"
    },
    {
      "ID": "oval:org.altlinux.errata:obj:20234390012",
      "Version": "1",
      "comment": "libqt5-widgets is installed",
      "Name": "libqt5-widgets"
    },
    {
      "ID": "oval:org.altlinux.errata:obj:20234390013",
      "Version": "1",
      "comment": "libqt5-xcbqpa is installed",
      "Name": "libqt5-xcbqpa"
    },
    {
      "ID": "oval:org.altlinux.errata:obj:20234390014",
      "Version": "1",
      "comment": "libqt5-xml is installed",
      "Name": "libqt5-xml"
    },
    {
      "ID": "oval:org.altlinux.errata:obj:20234390015",
      "Version": "1",
      "comment": "qt5-base-common is installed",
      "Name": "qt5-base-common"
    },
    {
      "ID": "oval:org.altlinux.errata:obj:20234390016",
      "Version": "1",
      "comment": "qt5-base-devel is installed",
      "Name": "qt5-base-devel"
    },
    {
      "ID": "oval:org.altlinux.errata:obj:20234390017",
      "Version": "1",
      "comment": "qt5-base-devel-static is installed",
      "Name": "qt5-base-devel-static"
    },
    {
      "ID": "oval:org.altlinux.errata:obj:20234390018",
      "Version": "1",
      "comment": "qt5-base-doc is installed",
      "Name": "qt5-base-doc"
    },
    {
      "ID": "oval:org.altlinux.errata:obj:20234390019",
      "Version": "1",
      "comment": "qt5-qtbase is installed",
      "Name": "qt5-qtbase"
    },
    {
      "ID": "oval:org.altlinux.errata:obj:20234390020",
      "Version": "1",
      "comment": "qt5-qtbase-gui is installed",
      "Name": "qt5-qtbase-gui"
    },
    {
      "ID": "oval:org.altlinux.errata:obj:20234390021",
      "Version": "1",
      "comment": "qt5-sql is installed",
      "Name": "qt5-sql"
    },
    {
      "ID": "oval:org.altlinux.errata:obj:20234390022",
      "Version": "1",
      "comment": "qt5-sql-interbase is installed",
      "Name": "qt5-sql-interbase"
    },
    {
      "ID": "oval:org.altlinux.errata:obj:20234390023",
      "Version": "1",
      "comment": "qt5-sql-mysql is installed",
      "Name": "qt5-sql-mysql"
    },
    {
      "ID": "oval:org.altlinux.errata:obj:20234390024",
      "Version": "1",
      "comment": "qt5-sql-odbc is installed",
      "Name": "qt5-sql-odbc"
    },
    {
      "ID": "oval:org.altlinux.errata:obj:20234390025",
      "Version": "1",
      "comment": "qt5-sql-postgresql is installed",
      "Name": "qt5-sql-postgresql"
    },
    {
      "ID": "oval:org.altlinux.errata:obj:20234390026",
      "Version": "1",
      "comment": "rpm-macros-qt5 is installed",
      "Name": "rpm-macros-qt5"
    }
  ]
}