{
  "TextFileContent54Objects": [
    {
      "ID": "oval:org.altlinux.errata:obj:4001",
      "Version": "1",
      "comment": "Evaluate `/etc/os-release` file content",
      "Path": {
        "dataType": "string",
        "Text": "/etc"
      },
      "Filepath": {
        "Datatype": "string",
        "Text": "os-release"
      },
      "Pattern": {
        "Datatype": "string",
        "Operation": "pattern match",
        "Text": "cpe:\\/o:alt:sp(?:server|workstation):(\\d+)"
      },
      "Instance": {
        "Datatype": "int",
        "Text": "1"
      }
    }
  ],
  "RpmInfoObjects": [
    {
      "ID": "oval:org.altlinux.errata:obj:20234357001",
      "Version": "1",
      "comment": "curl is installed",
      "Name": "curl"
    },
    {
      "ID": "oval:org.altlinux.errata:obj:20234357002",
      "Version": "1",
      "comment": "libcurl is installed",
      "Name": "libcurl"
    },
    {
      "ID": "oval:org.altlinux.errata:obj:20234357003",
      "Version": "1",
      "comment": "libcurl-devel is installed",
      "Name": "libcurl-devel"
    }
  ]
}