{
  "TextFileContent54Objects": [
    {
      "ID": "oval:org.altlinux.errata:obj:2001",
      "Version": "1",
      "comment": "Evaluate `/etc/os-release` file content",
      "Path": {
        "dataType": "string",
        "Text": "/etc"
      },
      "Filepath": {
        "Datatype": "string",
        "Text": "os-release"
      },
      "Pattern": {
        "Datatype": "string",
        "Operation": "pattern match",
        "Text": "cpe:\\/o:alt:(?!sp)[a-z\\-]+:p?(\\d+)(?:\\.\\d)*"
      },
      "Instance": {
        "Datatype": "int",
        "Text": "1"
      }
    }
  ],
  "RpmInfoObjects": [
    {
      "ID": "oval:org.altlinux.errata:obj:20234299001",
      "Version": "1",
      "comment": "libqt5-location is installed",
      "Name": "libqt5-location"
    },
    {
      "ID": "oval:org.altlinux.errata:obj:20234299002",
      "Version": "1",
      "comment": "libqt5-positioning is installed",
      "Name": "libqt5-positioning"
    },
    {
      "ID": "oval:org.altlinux.errata:obj:20234299003",
      "Version": "1",
      "comment": "libqt5-positioningquick is installed",
      "Name": "libqt5-positioningquick"
    },
    {
      "ID": "oval:org.altlinux.errata:obj:20234299004",
      "Version": "1",
      "comment": "qt5-location-common is installed",
      "Name": "qt5-location-common"
    },
    {
      "ID": "oval:org.altlinux.errata:obj:20234299005",
      "Version": "1",
      "comment": "qt5-location-devel is installed",
      "Name": "qt5-location-devel"
    },
    {
      "ID": "oval:org.altlinux.errata:obj:20234299006",
      "Version": "1",
      "comment": "qt5-location-doc is installed",
      "Name": "qt5-location-doc"
    }
  ]
}